sb6.py
sb6-0.0.9.dist-info/LICENSE
sb6-0.0.9.dist-info/METADATA
sb6-0.0.9.dist-info/WHEEL
sb6-0.0.9.dist-info/top_level.txt
sb6-0.0.9.dist-info/RECORD
