Metadata-Version: 2.1
Name: sb6
Version: 0.0.9
Summary: chatbot
Author: aiml department
Author-email: aiml@gmail.com
License: MIT
Keywords: sb6
Classifier: Programming Language :: Python :: 3
Classifier: License :: OSI Approved :: MIT License
Classifier: Operating System :: OS Independent
Requires-Python: >=3.7
License-File: LICENSE
Requires-Dist: opencv-python
Requires-Dist: scikit-learn
